BlynkWrapper/Errors.py
BlynkWrapper/Wrapper.py
BlynkWrapper/__init__.py
BlynkWrapper-0.0.1.dist-info/LICENSE
BlynkWrapper-0.0.1.dist-info/METADATA
BlynkWrapper-0.0.1.dist-info/WHEEL
BlynkWrapper-0.0.1.dist-info/top_level.txt
BlynkWrapper-0.0.1.dist-info/RECORD
