Metadata-Version: 2.1
Name: BlynkWrapper
Version: 0.0.1
Summary: A Python package to simplify working with Blynk
Home-page: https://github.com/fazalfarhan01/Blynk-Python-Wrapper
Author: Mohamed Farhan Fazal
Author-email: fazal.farhan@gmail.com
License: UNKNOWN
Project-URL: Bug Tracker, https://github.com/fazalfarhan01/Blynk-Python-Wrapper/issues
Platform: UNKNOWN
Classifier: Programming Language :: Python :: 3
Classifier: License :: OSI Approved :: MIT License
Classifier: Operating System :: OS Independent
Requires-Python: >=3.6
